xia_api_flask/__init__.py
xia_api_flask/rest.cpython-311-darwin.so
xia_api_flask-0.1.20.dist-info/LICENSE.txt
xia_api_flask-0.1.20.dist-info/METADATA
xia_api_flask-0.1.20.dist-info/WHEEL
xia_api_flask-0.1.20.dist-info/top_level.txt
xia_api_flask-0.1.20.dist-info/RECORD
