Metadata-Version: 2.1
Name: xia-api-flask
Version: 0.1.20
Summary: UNKNOWN
Home-page: https://develop.x-i-a.com/docs/xia-api-flask/0.1.20/index.html
Author: X-I-A
Author-email: admin@x-i-a.com
License: UNKNOWN
Platform: UNKNOWN
Requires-Python: >=3.9
License-File: LICENSE.txt
Requires-Dist: Flask
Requires-Dist: xia-api
Requires-Dist: xia-token-flask
Requires-Dist: xia-broadcast-listener
